__init__.py
agilent_vacuum/__init__.py
agilent_vacuum/commands.py
agilent_vacuum/communication.py
agilent_vacuum/exceptions.py
agilent_vacuum/ipc_mini.py
agilent_vacuum/twis_torr_74.py
agilent_vacuum-0.1.0.dist-info/LICENSE
agilent_vacuum-0.1.0.dist-info/METADATA
agilent_vacuum-0.1.0.dist-info/WHEEL
agilent_vacuum-0.1.0.dist-info/top_level.txt
agilent_vacuum-0.1.0.dist-info/RECORD
