Metadata-Version: 2.2
Name: agilent_vacuum
Version: 0.1.0
Summary: A package for commuincation with various Agilent Vacuum pump controllers and sensors.
Author-email: Ulrik Södergreb <ulrik.sodergren@luxbright.com>
License: MIT License
Project-URL: Homepage, https://github.com/luxbright-com/vacuum_interfaces
Project-URL: Bug Tracker, https://github.com/luxbright-com/vacuum_interfaces/issues
Classifier: Programming Language :: Python :: 3.9
Classifier: Programming Language :: Python :: 3.10
Classifier: Programming Language :: Python :: 3.11
Classifier: Programming Language :: Python :: 3.12
Classifier: License :: OSI Approved :: MIT License
Classifier: Operating System :: OS Independent
Classifier: Intended Audience :: Developers
Classifier: Development Status :: 4 - Beta
Requires-Python: >=3.9
License-File: LICENSE
Requires-Dist: aiofiles>=24.1
Requires-Dist: aioserial>=1.3
Requires-Dist: pyserial>=3.5
Requires-Dist: tenacity>=9.0
Provides-Extra: test
Requires-Dist: pytest>8.3; extra == "test"
Requires-Dist: pytest-asyncio>0.24; extra == "test"
Requires-Dist: pytest-timeout>2.3; extra == "test"
Provides-Extra: dev
Requires-Dist: ruff; extra == "dev"
Requires-Dist: twine; extra == "dev"
